psgpsg/__init__.py
psgpsg/psgpsg.py
psgpsg-1.0.0.dist-info/METADATA
psgpsg-1.0.0.dist-info/WHEEL
psgpsg-1.0.0.dist-info/entry_points.txt
psgpsg-1.0.0.dist-info/top_level.txt
psgpsg-1.0.0.dist-info/RECORD
