Metadata-Version: 2.1
Name: psgpsg
Version: 1.0.0
Summary: Runs sg.main() using whatever default PySimpleGUI.py your system picks up.
Home-page: https://github.com/PySimpleGUI/PySimpleGUI
Author: PySimpleGUI
Author-email: PySimpleGUI@PySimpleGUI.org
License: UNKNOWN
Platform: UNKNOWN
Classifier: Programming Language :: Python :: 3
Classifier: Programming Language :: Python :: 3.4
Classifier: Programming Language :: Python :: 3.5
Classifier: Programming Language :: Python :: 3.6
Classifier: Programming Language :: Python :: 3.7
Classifier: Programming Language :: Python :: 3.8
Classifier: Programming Language :: Python :: 3.9
Classifier: Programming Language :: Python :: 3.10
Classifier: Programming Language :: Python :: 3.11
Classifier: License :: OSI Approved :: GNU Lesser General Public License v3 or later (LGPLv3+)
Classifier: Topic :: Multimedia :: Graphics
Classifier: Topic :: Multimedia :: Graphics :: Graphics Conversion
Classifier: Topic :: Scientific/Engineering :: Image Processing
Classifier: Topic :: Utilities
Classifier: Operating System :: OS Independent
Requires-Dist: PySimpleGUI
